voxscribe/__init__.py
voxscribe/py.typed
voxscribe/voxscribe.py
voxscribe-1.1.2.dist-info/METADATA
voxscribe-1.1.2.dist-info/WHEEL
voxscribe-1.1.2.dist-info/licenses/LICENSE.txt
voxscribe-1.1.2.dist-info/RECORD
