Metadata-Version: 2.1
Name: voxscribe
Version: 1.1.2
Summary: Extract text from .wav and .mp3 files.
Project-URL: Homepage, https://github.com/matt-manes/voxscribe
Project-URL: Documentation, https://github.com/matt-manes/voxscribe/tree/main/docs
Project-URL: Source code, https://github.com/matt-manes/voxscribe/tree/main/src/voxscribe
Author: Matt Manes
License-File: LICENSE.txt
Keywords: audio,speech,text
Classifier: License :: OSI Approved :: MIT License
Classifier: Operating System :: OS Independent
Classifier: Programming Language :: Python :: 3
Requires-Python: >=3.10
Requires-Dist: pydub
Requires-Dist: pytest
Requires-Dist: requests
Requires-Dist: speechrecognition
Requires-Dist: whosyouragent
